[
	{ "t": 950, "t2": 1290, "txt": "Carry" },
	{ "t": 1300, "t2": 1560, "txt": " on," },
	{ "t": 1570, "t2": 1810, "txt": " my" },
	{ "t": 1900, "t2": 2390, "txt": " wayward" },
	{ "t": 2400, "t2": 2750, "txt": " son." },
	{ "t": 3200, "t2": 3550, "txt": " Don't" },
	{ "t": 3560, "t2": 3950, "txt": " fear" },
	{ "t": 3960, "t2": 4080, "txt": " the" },
	{ "t": 4090, "t2": 4680, "txt": " reaper." },
	{ "t": 5310, "t2": 5610, "txt": " I'm" },
	{ "t": 5650, "t2": 5870, "txt": " back" },
	{ "t": 5880, "t2": 6070, "txt": " in" },
	{ "t": 6080, "t2": 6390, "txt": " black," },
	{ "t": 6540, "t2": 7220, "txt": " bitches." }
]
